Workbook

Sheet Resumen de exportación
B3: Este documento se exportó de Numbers. Cada tabla se convirtió en una hoja de cálculo de Excel. Los demás objetos de las hojas de Numbers se colocaron en distintas hojas de cálculo. Recuerda que el cálculo de fórmulas puede ser diferente en Excel.
B7: Nombre de hoja de Numbers | C7: Nombre de tabla de Numbers | D7: Nombre de hoja de cálculo de Excel
B9: Proy. X Etapas
C10: Proyecciones financieras por Etapas (O, R, U) | D10: Proy. X Etapas - Proyecciones f
B11: Rentabilidad
C12: Tabla 1 | D12: Rentabilidad

Sheet Proy. X Etapas - Proyecciones f
A1: Proyecciones financieras por Etapas (O, R, U)
C2: Unidades (U) | D2: Tarifa (R) | E2: Ocupación (O) semanal (días) | G2: Ocupación mensual (días) | H2: Ocupación mensual (%) | I2: Ingreso semanal (en pesos) | J2: Ingreso semanal (en US$) | K2: # semana | L2: Ingreso mensual (en US$) | M2: Ingreso anual (en US$) | O2: Rentabilidad
A3: Escenario actual | C3: 4 | D3: 655000 | E3: 1 | G3: {=C3*E3*4} -> 16 | H3: {=G3/120} -> 0.13333333 | I3: {=C3*D3*E3} -> 2620000 | J3: {=I3/3200} -> 818.75 | K3: 4 | L3: {=J3*K3} -> 3275 | M3: {=L3*12} -> 39300 | O3: {='Rentabilidad'!H3} -> 2.4625e-06 | Q3: Es el punto de equilibrio actual
A5: Escenario (O) | C5: 4 | D5: 655000 | E5: 2.5 | G5: {=C5*E5*4} -> 40 | H5: {=G5/120} -> 0.33333333 | I5: {=C5*D5*E5} -> 6550000 | J5: {=I5/3200} -> 2046.875 | K5: 4 | L5: {=J5*K5} -> 8187.5 | M5: {=L5*12} -> 98250 | O5: {='Rentabilidad'!H4} -> 0.10039293 | Q5: El % de rentabilidad incluye la inversión total
L7: Ingresos adicionales (O) | M7: {=M5-M3} -> 58950
A9: Escenario (O+R) | C9: 4 | D9: {=D5+(D5*50%)} -> 982500 | E9: 2.5 | G9: {=C9*E9*4} -> 40 | H9: {=G9/120} -> 0.33333333 | I9: {=C9*D9*E9} -> 9825000 | J9: {=I9/3200} -> 3070.3125 | K9: 4 | L9: {=J9*K9} -> 12281.25 | M9: {=L9*12} -> 147375 | O9: {='Rentabilidad'!H5} -> 0.13860759 | Q9: El % de rentabilidad incluye la inversión total
L11: Ingresos adicionales (O+R) | M11: {=M9-M3} -> 108075
A13: Escenario (O+R+U) | C13: 7 | D13: {=D9+(D9*50%)} -> 1473750 | E13: 2.5 | G13: {=C13*E13*4} -> 70 | H13: {=G13/120} -> 0.58333333 | I13: {=C13*D13*E13} -> 25790625 | J13: {=I13/3200} -> 8059.5703 | K13: 4 | L13: {=J13*K13} -> 32238.281 | M13: {=L13*12} -> 386859.38 | O13: {='Rentabilidad'!H6} -> 0.21178734 | Q13: El % de rentabilidad incluye la inversión total
L15: Ingresos adicionales (O+R+U)) | M15: {=M13-M7} -> 327909.38

Sheet Rentabilidad
A1: Tabla 1
B2: Inversión COP | C2: Inversión US$ | D2: Ingresos Brutos | E2: Costos Op. | F2: Ingresos Netos (COP) | G2: Ingresos Netos (US$) | H2: Rentabilidad (%)
A3: Escenario inicial | B3: 2000000000 | C3: {=B3/3200} -> 625000 | D3: {='Proy. X Etapas - Proyecciones f'!M3} -> 39300 | E3: {=110000000/3200} -> 34375 | F3: {=D3*3200} -> 125760000 | G3: {=D3-E3} -> 4925 | H3: {=G3/B3} -> 2.4625e-06
A4: Escenario “O" | B4: 36000000 | C4: {=(B3+B4)/3200} -> 636250 | D4: {='Proy. X Etapas - Proyecciones f'!M5} -> 98250 | E4: {=110000000/3200} -> 34375 | F4: {=D4*3200} -> 314400000 | G4: {=D4-E4} -> 63875 | H4: {=G4/C4} -> 0.10039293
A5: Escenario “O+R" | B5: 176000000 | C5: {=(B3+B4+B5)/3200} -> 691250 | D5: {='Proy. X Etapas - Proyecciones f'!M9} -> 147375 | E5: {=E4*1.5} -> 51562.5 | F5: {=D5*3200} -> 471600000 | G5: {=D5-E5} -> 95812.5 | H5: {=G5/C5} -> 0.13860759
A6: Escenario “O+R+U” | B6: 1296000000 | C6: {=(B3+B4+B5+B6)/3200} -> 1096250 | D6: {='Proy. X Etapas - Proyecciones f'!M13} -> 386859.38 | E6: {=E5*3} -> 154687.5 | F6: {=D6*3200} -> 1237950000 | G6: {=D6-E6} -> 232171.88 | H6: {=G6/C6} -> 0.21178734
